{
  "info": {
    "name": "SIGE Students API",
    "_postman_id": "b9a7cdb8-1234-4e7a-bd3b-fake123456789",
    "description": "Colección para probar operaciones CRUD de la tabla 'students' en el backend Flask del proyecto SIGE. Incluye pruebas con ID automático y personalizado.",
    "schema": "https://schema.getpostman.com/json/collection/v2.1.0/collection.json"
  },
  "item": [
    {
      "name": "GET - Obtener todos los estudiantes",
      "request": {
        "method": "GET",
        "header": [],
        "url": {
          "raw": "http://localhost:8000/students",
          "protocol": "http",
          "host": ["localhost"],
          "port": "8000",
          "path": ["students"]
        }
      }
    },
    {
      "name": "GET - Obtener estudiante por ID",
      "request": {
        "method": "GET",
        "header": [],
        "url": {
          "raw": "http://localhost:8000/students/3",
          "protocol": "http",
          "host": ["localhost"],
          "port": "8000",
          "path": ["students", "3"]
        }
      }
    },
    {
      "name": "POST - Crear nuevo estudiante",
      "request": {
        "method": "POST",
        "header": [
          {
            "key": "Content-Type",
            "value": "application/json"
          }
        ],
        "body": {
          "mode": "raw",
          "raw": "{\n    \"student_id\": 10,\n    \"first_name\": \"Laura\",\n    \"last_name\": \"Martínez\",\n    \"grade_level\": \"3°\",\n    \"group_name\": \"C\",\n    \"birth_date\": \"2017-08-10\",\n    \"parent_id\": 1,\n    \"status\": \"activo\"\n}"
        },
        "url": {
          "raw": "http://localhost:8000/students",
          "protocol": "http",
          "host": ["localhost"],
          "port": "8000",
          "path": ["students"]
        }
      }
    },
    {
      "name": "PUT - Actualizar estudiante existente",
      "request": {
        "method": "PUT",
        "header": [
          {
            "key": "Content-Type",
            "value": "application/json"
          }
        ],
        "body": {
          "mode": "raw",
          "raw": "{\n    \"first_name\": \"Laura Elena\",\n    \"last_name\": \"Martínez\",\n    \"grade_level\": \"3°\",\n    \"group_name\": \"A\",\n    \"status\": \"activo\"\n}"
        },
        "url": {
          "raw": "http://localhost:8000/students/4",
          "protocol": "http",
          "host": ["localhost"],
          "port": "8000",
          "path": ["students", "4"]
        }
      }
    },
    {
      "name": "DELETE - Eliminar estudiante",
      "request": {
        "method": "DELETE",
        "header": [],
        "url": {
          "raw": "http://localhost:8000/students/3",
          "protocol": "http",
          "host": ["localhost"],
          "port": "8000",
          "path": ["students", "3"]
        }
      }
    }
  ]
}